jje_cli/__init__.py
jje_cli/cli.py
jje_cli-0.1.4.dist-info/METADATA
jje_cli-0.1.4.dist-info/WHEEL
jje_cli-0.1.4.dist-info/entry_points.txt
jje_cli-0.1.4.dist-info/top_level.txt
jje_cli-0.1.4.dist-info/RECORD
