Metadata-Version: 2.1
Name: jje_cli
Version: 0.1.4
Summary: A simple to use CLI tool for creating a Vuejs project scaffold with Django as backend
Home-page: https://github.com/yourusername/jje_cli
Author: John Gbaya-kokoya Jr
Author-email: gbayakokoyajohnjr@gmail.com
Classifier: Programming Language :: Python :: 3
Classifier: License :: OSI Approved :: MIT License
Classifier: Operating System :: OS Independent
Requires-Python: >=3.6
Requires-Dist: click
Requires-Dist: GitPython
